MANIFEST.in
README
lsswap.py
setup.py
bin/lsswap
lsswap.egg-info/PKG-INFO
lsswap.egg-info/SOURCES.txt
lsswap.egg-info/dependency_links.txt
lsswap.egg-info/requires.txt
lsswap.egg-info/top_level.txt