Metadata-Version: 1.0
Name: lsswap
Version: 0.2
Summary: lsswap aim to show all the swap information on a GNU/Linux machine
Home-page: https://github.com/sxd/sysadmin-tools
Author: Jonathan Gonzalez V
Author-email: jgonzalez@linets.cl
License: UNKNOWN
Platform: UNKNOWN
